{"o": 231, "ɾ": 2128, "u": 2628, "p": 1015, "aː": 1467, "ʈ": 1095, "b": 994, "oː": 676, "l": 1233, "e": 1190, "m": 2324, "i": 3704, "tʃː": 291, "t̪ː": 316, "a": 10051, "n̪": 1660, "t̪": 1412, "d̪": 1297, "ʋ": 1174, "n̪ː": 585, "ɲ": 46, "iː": 255, "lː": 104, "r": 468, "ɳ": 660, "eː": 485, "j": 1217, "ɭː": 90, "ɖ": 420, "s": 590, "ɲː": 129, "k": 1599, "ɡ": 1280, "uː": 200, "ɭ": 650, "pː": 90, "ʂ": 259, "mː": 43, "ɻ": 198, "ʈː": 414, "kː": 404, "tʃ": 240, "t̪ʰ": 77, "d̪ʱ": 143, "ŋː": 185, "ʃ": 162, "h": 90, "ɳː": 60, "bʱ": 133, "ɡʱ": 11, "kʰ": 42, "ŋ": 63, "ʈʰ": 20, "pʰ": 133, "ɟ": 156, "ai": 88, "tʃʰː": 6, "t̪ʰː": 1, "au": 13}