{"k": 668, "ɡ": 731, "m": 663, "b": 678, "p": 641, "f": 969, "v": 625, "d̪": 1241, "t̪": 1322, "l": 1470, "ʔ": 169, "w": 85, "u": 88, "uː": 7, "ħ": 168, "i": 1494, "j": 1058, "a": 531, "iː": 1, "o": 85, "s": 700, "z": 603, "aː": 143, "ʃ": 56, "n": 556, "ɪː": 6, "dʒ": 141, "tʃ": 98, "lː": 44, "ew": 27, "oː": 12, "sː": 60, "e": 156, "r": 335, "nː": 24, "awː": 4, "ts": 11, "aw": 4, "t̪ː": 54, "d̪ː": 53, "rː": 72, "ʃː": 12, "eː": 3, "ajː": 8, "zː": 23, "mː": 4, "ː": 12, "dʒː": 2, "iw": 5, "ej": 1, "pː": 14, "bː": 12, "tʃː": 2, "aj": 2}